krakenforwarder/__init__.py
krakenforwarder/forwarder.py
krakenforwarder/listener.py
krakenforwarder/util.py
krakenforwarder-0.8.dist-info/LICENSE
krakenforwarder-0.8.dist-info/METADATA
krakenforwarder-0.8.dist-info/WHEEL
krakenforwarder-0.8.dist-info/top_level.txt
krakenforwarder-0.8.dist-info/RECORD
