Metadata-Version: 2.1
Name: krakenforwarder
Version: 0.8
Summary: Forwards trades from Kraken.com to TCP port
Home-page: https://github.com/supercuiller/krakenforwarder
Author: Thibaut Castaings, Zao Wu
Author-email: castaings.t@protonmail.com
License: MIT
Platform: UNKNOWN
Requires-Dist: pyzmq
Requires-Dist: schema
Requires-Dist: pyyaml
Requires-Dist: krakenex
Requires-Dist: requests
Requires-Dist: python-dateutil
